{
  "featured": [{
    "date": "2018/04/16",
    "items": [0, 1, 4, 2, 3]
  }, {
    "date": "2018/04/09",
    "items": [0, 1, 4, 2, 3]
  }, {
    "date": "2018/04/02",
    "items": [0, 1, 4, 2, 3]
  }],
  "images": "/db/tools/logos/",
  "items": [{
    "id": "0",
    "title": "SpeedCurve",
    "meta": "Performance audits",
    "url": "https://speedcurve.com/",
    "color": "#CCEBFF"
  }, {
    "id": "1",
    "title": "Bugsnag",
    "meta": "Error tracking",
    "url": "https://www.bugsnag.com/",
    "color": "#CCD8FF"
  }, {
    "id": "2",
    "title": "Sentry",
    "meta": "Error tracking",
    "url": "https://sentry.io/",
    "color": "#D5CCFF"
  }, {
    "id": "3",
    "title": "Rollbar",
    "meta": "Error tracking",
    "url": "https://rollbar.com/",
    "color": "#E6F9FF"
  }, {
    "id": "4",
    "title": "BrowserStack",
    "meta": "Browser testing",
    "url": "https://www.browserstack.com/",
    "color": "#FFE0CC"
  }]
}